examples/__init__.py
examples/simple.py
marquez_client/__init__.py
marquez_client/client.py
marquez_client/clients.py
marquez_client/constants.py
marquez_client/errors.py
marquez_client/models.py
marquez_client/utils.py
tests/__init__.py
tests/test_marquez_client.py
tests/test_marquez_clients.py
tests/test_utils.py
swar00pduthks_marquez_python-0.51.2.dist-info/METADATA
swar00pduthks_marquez_python-0.51.2.dist-info/WHEEL
swar00pduthks_marquez_python-0.51.2.dist-info/top_level.txt
swar00pduthks_marquez_python-0.51.2.dist-info/RECORD
